qytools/__init__.py
qytools/db_maintain.py
qytools/db_read.py
qytools/stack.py
qytools/tools.py
qytools-0.1.2.dist-info/LICENSE
qytools-0.1.2.dist-info/METADATA
qytools-0.1.2.dist-info/WHEEL
qytools-0.1.2.dist-info/top_level.txt
qytools-0.1.2.dist-info/RECORD
