Metadata-Version: 2.1
Name: qytools
Version: 0.1.2
Summary: QLite3 database reading interface,general SQLite3 database warehousing interface,general SQLite3 database query assistant tool,stack
Home-page: https://gitee.com/yulin_qiu/projects
Author: Yulin Qiu
Author-email: x492876854@qq.com
License: UNKNOWN
Platform: UNKNOWN
Classifier: License :: OSI Approved :: MIT License
Classifier: Programming Language :: Python :: 3
